devops_ai/__init__.py
devops_ai/cli.py
devops_ai/core.py
devops_ai/dashboard.py
devops_ai/dashboard_original.py
devops_ai/env_loader.py
devops_ai/agents/__init__.py
devops_ai/agents/analyze_logs.py
devops_ai/agents/aws_mcp_use.py
devops_ai/agents/base_agent.py
devops_ai/agents/code_quality.py
devops_ai/agents/contributors.py
devops_ai/agents/dependency_check.py
devops_ai/agents/docker_generation.py
devops_ai/agents/grafana.py
devops_ai/agents/infra_suggest.py
devops_ai/agents/json_toolkit_retriver.py
devops_ai/agents/optimize.py
devops_ai/agents/repo_analyze.py
devops_ai/agents/security_scan.py
devops_ai/agents/test_automate_datasource.py
devops_ai/agents/aws/__init__.py
devops_ai/agents/aws/all_modules.json
devops_ai/agents/aws/aws_modules_params.json
devops_ai/agents/aws/aws_modules_returns.json
devops_ai/agents/mointoring/__init__.py
devops_ai/agents/mointoring/playbook.yml
devops_ai/agents/mointoring/roles/__init__.py
devops_ai/agents/mointoring/roles/monitoring/__init__.py
devops_ai/agents/mointoring/roles/monitoring/defaults/__init__.py
devops_ai/agents/mointoring/roles/monitoring/defaults/main.yml
devops_ai/agents/mointoring/roles/monitoring/tasks/__init__.py
devops_ai/agents/mointoring/roles/monitoring/tasks/main.yml
devops_ai/agents/mointoring/roles/monitoring/templates/__init__.py
devops_ai/agents/mointoring/roles/monitoring/templates/grafana.ini.j2
devops_ai/agents/mointoring/roles/monitoring/templates/prometheus.yml.j2
devops_ai/ansible_cli/__init__.py
devops_ai/ui/__init__.py
devops_ai/ui/panels.py
devops_ai/ui/tool_handlers.py
syntera_ai_cli-0.1.7.9.dist-info/LICENSE
syntera_ai_cli-0.1.7.9.dist-info/METADATA
syntera_ai_cli-0.1.7.9.dist-info/WHEEL
syntera_ai_cli-0.1.7.9.dist-info/entry_points.txt
syntera_ai_cli-0.1.7.9.dist-info/top_level.txt
syntera_ai_cli-0.1.7.9.dist-info/RECORD
